pygithubmanager/__init__.py
pygithubmanager/githubmanager.py
pygithubmanager/modules/__init__.py
pygithubmanager/modules/about.py
pygithubmanager/modules/create_repository.py
pygithubmanager/modules/local_repositories.py
pygithubmanager/modules/local_repository.py
pygithubmanager/modules/login.py
pygithubmanager/modules/overview.py
pygithubmanager/modules/repositories.py
pygithubmanager/modules/repository.py
pygithubmanager/modules/user.py
pygithubmanager/resources/icons/GitHub_Manager.png
pygithubmanager/resources/icons/dark_license.png
pygithubmanager/resources/icons/dark_ocultar.png
pygithubmanager/resources/icons/dark_open_book.png
pygithubmanager/resources/icons/dark_repo.png
pygithubmanager/resources/icons/dark_star.png
pygithubmanager/resources/icons/dark_visible.png
pygithubmanager/resources/icons/license.png
pygithubmanager/resources/icons/ocultar.png
pygithubmanager/resources/icons/open_book.png
pygithubmanager/resources/icons/repo.png
pygithubmanager/resources/icons/star.png
pygithubmanager/resources/icons/visible.png
pygithubmanager/resources/icons/yellow_star.png
pygithubmanager/ui/Ui_about.py
pygithubmanager/ui/Ui_login.py
pygithubmanager/ui/Ui_main.py
pygithubmanager/ui/__init__.py
pygithubmanager/ui/aboutwindow.ui
pygithubmanager/ui/loginwindow.ui
pygithubmanager/ui/mainwindow.ui
pygithubmanager/ui/widgets/Ui_clone.py
pygithubmanager/ui/widgets/Ui_create_repository.py
pygithubmanager/ui/widgets/Ui_edit_profile.py
pygithubmanager/ui/widgets/Ui_edit_repository.py
pygithubmanager/ui/widgets/Ui_file_template.py
pygithubmanager/ui/widgets/Ui_issue_template.py
pygithubmanager/ui/widgets/Ui_local_repositories.py
pygithubmanager/ui/widgets/Ui_local_repository.py
pygithubmanager/ui/widgets/Ui_local_repository_template.py
pygithubmanager/ui/widgets/Ui_overview.py
pygithubmanager/ui/widgets/Ui_popular_repositories.py
pygithubmanager/ui/widgets/Ui_repositories.py
pygithubmanager/ui/widgets/Ui_repository.py
pygithubmanager/ui/widgets/Ui_repository_template.py
pygithubmanager-1.0.1.dist-info/LICENSE
pygithubmanager-1.0.1.dist-info/WHEEL
pygithubmanager-1.0.1.dist-info/METADATA
pygithubmanager-1.0.1.dist-info/RECORD
