Metadata-Version: 2.1
Name: pygithubmanager
Version: 1.0.1
Summary: GitHub desktop version created with Python
License: GNU General Public License v3.0
Author: DomiTP
Requires-Python: >=3.7,<3.11
Classifier: License :: Other/Proprietary License
Classifier: Programming Language :: Python :: 3
Classifier: Programming Language :: Python :: 3.10
Classifier: Programming Language :: Python :: 3.7
Classifier: Programming Language :: Python :: 3.8
Classifier: Programming Language :: Python :: 3.9
Requires-Dist: GitPython (>=3.1.27,<4.0.0)
Requires-Dist: PyGithub (>=1.55,<2.0)
Requires-Dist: PySide6 (>=6.3.0,<7.0.0)
Requires-Dist: QtAwesome (>=1.1.1,<2.0.0)
Requires-Dist: matplotlib (>=3.5.2,<4.0.0)
Requires-Dist: pygit2 (>=1.9.2,<2.0.0)
